aws_sentinel/__init__.py
aws_sentinel/ascii_art.py
aws_sentinel/cli.py
aws_sentinel/core.py
aws_sentinel/nlp.py
aws_sentinel/utils.py
tests/__init__.py
tests/test_aws_sentinel.py
tests/test_nlp.py
aws_sentinel-0.1.2.dist-info/METADATA
aws_sentinel-0.1.2.dist-info/WHEEL
aws_sentinel-0.1.2.dist-info/entry_points.txt
aws_sentinel-0.1.2.dist-info/top_level.txt
aws_sentinel-0.1.2.dist-info/RECORD
