Metadata-Version: 2.4
Name: aws-sentinel
Version: 0.1.2
Summary: A security scanner for AWS resources
Home-page: https://github.com/rishabkumar7/aws-sentinel
Author: Rishab Kumar
Author-email: rishabkumar7@gmail.com
Classifier: Programming Language :: Python :: 3
Classifier: License :: OSI Approved :: MIT License
Classifier: Operating System :: OS Independent
Requires-Python: >=3.9
Requires-Dist: boto3>=1.34.0
Requires-Dist: click>=8.0.0
Requires-Dist: prettytable>=2.0.0
Requires-Dist: colorama>=0.4.4
Dynamic: author
Dynamic: author-email
Dynamic: classifier
Dynamic: description
Dynamic: description-content-type
Dynamic: home-page
Dynamic: requires-dist
Dynamic: requires-python
Dynamic: summary
